{
    "Ar36": {
        "error": 0.0022202088266821641, 
        "fit": "linear", 
        "value": 0.027037805523727906
    }, 
    "Ar37": {
        "error": 0.13576942427372202, 
        "fit": "linear", 
        "value": 0.18965369107999042
    }, 
    "Ar38": {
        "error": 0.31848890562866544, 
        "fit": "linear", 
        "value": 0.25154976535468654
    }, 
    "Ar39": {
        "error": 0.069297309604518145, 
        "fit": "linear", 
        "value": 12.037981606838089
    }, 
    "Ar40": {
        "error": 0.63506047196638205, 
        "fit": "linear", 
        "value": 2244.152862902426
    }, 
    "Ar41": {
        "error": 0.13964089487470527, 
        "fit": "average_SEM", 
        "value": -0.032738009540383549
    }
}